instance_selector/__init__.py
instance_selector/apps.py
instance_selector/blocks.py
instance_selector/constants.py
instance_selector/edit_handlers.py
instance_selector/exceptions.py
instance_selector/registry.py
instance_selector/selectors.py
instance_selector/urls.py
instance_selector/views.py
instance_selector/wagtail_hooks.py
instance_selector/widgets.py
instance_selector/static/instance_selector/instance-selector-controller.js
instance_selector/static/instance_selector/instance_selector.css
instance_selector/static/instance_selector/instance_selector_embed.js
instance_selector/static/instance_selector/instance_selector_telepath.js
instance_selector/static/instance_selector/instance_selector_widget.js
instance_selector/templates/instance_selector/instance_selector_embed.html
instance_selector/templates/instance_selector/instance_selector_widget.html
instance_selector/templates/instance_selector/instance_selector_widget_display.html
wagtail_instance_selector-3.1.1.dist-info/licenses/LICENSE
wagtail_instance_selector-3.1.1.dist-info/METADATA
wagtail_instance_selector-3.1.1.dist-info/WHEEL
wagtail_instance_selector-3.1.1.dist-info/top_level.txt
wagtail_instance_selector-3.1.1.dist-info/RECORD
