Metadata-Version: 2.4
Name: wagtail-instance-selector
Version: 3.1.1
Summary: A widget for Wagtail's admin that allows you to create and select related items
Author-email: The Interaction Consortium <studio@interaction.net.au>
Maintainer-email: The Interaction Consortium <studio@interaction.net.au>
License: MIT License
Project-URL: homepage, https://github.com/ixc/wagtail-instance-selector
Project-URL: issues, https://github.com/ixc/wagtail-instance-selector/issues
Project-URL: repository, https://github.com/ixc/wagtail-instance-selector.git
Project-URL: changelog, https://github.com/ixc/wagtail-instance-selector/blob/main/CHANGELOG.md
Keywords: wagtail,instance,selector
Classifier: Development Status :: 5 - Production/Stable
Classifier: Intended Audience :: Developers
Classifier: Intended Audience :: End Users/Desktop
Classifier: Environment :: Web Environment
Classifier: Framework :: Django
Classifier: Framework :: Django :: 3.2
Classifier: Framework :: Django :: 4.2
Classifier: Framework :: Django :: 5.1
Classifier: Framework :: Wagtail
Classifier: Framework :: Wagtail :: 6
Classifier: Framework :: Wagtail :: 7
Classifier: License :: OSI Approved :: MIT License
Classifier: Operating System :: OS Independent
Classifier: Programming Language :: Python :: 3
Classifier: Programming Language :: Python :: 3.9
Classifier: Programming Language :: Python :: 3.10
Classifier: Programming Language :: Python :: 3.11
Classifier: Programming Language :: Python :: 3.12
Classifier: Programming Language :: Python :: 3.13
Classifier: Topic :: Utilities
Requires-Python: >=3.9
License-File: LICENSE
Requires-Dist: wagtail>=6.3
Requires-Dist: wagtail-modeladmin
Provides-Extra: testing
Requires-Dist: django_webtest; extra == "testing"
Provides-Extra: dev
Requires-Dist: django>=4.2; extra == "dev"
Requires-Dist: ruff==0.12.12; extra == "dev"
Requires-Dist: ipdb<1.0,>=0.13; extra == "dev"
Dynamic: license-file
